vegi/__init__.py
vegi/colormaps.py
vegi/utils.py
vegi-0.1.0.dist-info/WHEEL
vegi-0.1.0.dist-info/METADATA
vegi-0.1.0.dist-info/RECORD
