Metadata-Version: 2.1
Name: vegi
Version: 0.1.0
Summary: Vegetation Index Library
Author: mitch3x3
Author-email: mitch3x3@github.com
Requires-Python: >=3.8,<4.0
Classifier: Programming Language :: Python :: 3
Classifier: Programming Language :: Python :: 3.8
Requires-Dist: numpy (>=1.18.5,<2.0.0)
Requires-Dist: rasterio (>=1.1.5,<2.0.0)
